nyord_vpn/__init__.py
nyord_vpn/__main__.py
nyord_vpn/_templates.py
nyord_vpn/_utils.py
nyord_vpn/base.py
nyord_vpn/client.py
nyord_vpn/models.py
nyord_vpn/utils.py
nyord_vpn/data/countries.json
nyord_vpn/data/country_ids.json
nyord_vpn/scripts/__init__.py
nyord_vpn/scripts/update_countries.py
nyord_vpn-0.1.0.dist-info/LICENSE
nyord_vpn-0.1.0.dist-info/METADATA
nyord_vpn-0.1.0.dist-info/WHEEL
nyord_vpn-0.1.0.dist-info/entry_points.txt
nyord_vpn-0.1.0.dist-info/top_level.txt
nyord_vpn-0.1.0.dist-info/RECORD
